spore_drive/__init__.py
spore_drive/clients.py
spore_drive/config.py
spore_drive/drive.py
spore_drive/operations.py
spore_drive/service_manager.py
spore_drive/types.py
spore_drive/utils.py
tests/__init__.py
tests/test_config_integration.py
tests/test_drive.py
tests/test_health_check.py
tests/test_imports.py
tests/test_mock_server.py
tests/test_operations_integration.py
tests/test_operations_unit.py
tests/test_service_manager.py
tests/test_simple.py
tests/test_utils.py
spore_drive-0.1.1.dist-info/METADATA
spore_drive-0.1.1.dist-info/WHEEL
spore_drive-0.1.1.dist-info/top_level.txt
spore_drive-0.1.1.dist-info/RECORD
